sabine/__init__.py
sabine-0.0.0.dist-info/METADATA
sabine-0.0.0.dist-info/WHEEL
sabine-0.0.0.dist-info/top_level.txt
sabine-0.0.0.dist-info/RECORD
